{"id":"75a9bbec-04f8-464b-b6cc-c094fc5244d3","entity_type":"rule","agent":"cli","timestamp":"2026-01-17T20:08:41.615037185Z","data":{"entity":{"action":{},"agent":"cli","condition":{},"created_at":"2026-01-17T20:08:41.615037185Z","description":"All git commits must reference a valid Engram task UUID in the commit message using format: 'commit message [uuid]'. This ensures traceability and maintains development context.","entity_types":[],"id":"75a9bbec-04f8-464b-b6cc-c094fc5244d3","priority":"high","rule_type":"validation","status":"active","title":"Engram Task Reference Requirement","updated_at":"2026-01-17T20:24:21.338135796Z"}},"content_hash":"8ebe0822ed957802d873ea99646f290d6c3a94fc3add0d3cebe3e6410f91e5d0","size_bytes":506,"tags":[],"references":[],"metadata":{}}