{"id":"7dfffcb7-0874-48a3-8fb3-89313d1be4aa","entity_type":"task","agent":"default","timestamp":"2026-01-18T03:56:13.059345633Z","data":{"entity":{"agent":"default","description":"","end_time":null,"id":"7dfffcb7-0874-48a3-8fb3-89313d1be4aa","priority":"high","start_time":"2026-01-18T03:56:13.059345633Z","status":"todo","title":"Validate eBPF kernel program compatibility in NixOS VM environment"}},"content_hash":"2538796c2e393ba130b0f428ad4b370836c14dcb914209256c9369ff203260b5","size_bytes":264,"tags":[],"references":[],"metadata":{}}